Metadata-Version: 1.0
Name: templer.core
Version: 1.0b3
Summary: Core functionality for the templer tool
Home-page: http://svn.plone.org/svn/collective/
Author: Cris Ewing
Author-email: cewing@sound-data.com
License: GPL version 2
Keywords: web zope command-line skeleton project
Platform: Any
Classifier: Development Status :: 4 - Beta
Classifier: Framework :: Zope2
Classifier: Framework :: Zope3
Classifier: Framework :: Plone
Classifier: Framework :: Buildout
Classifier: Intended Audience :: Developers
Classifier: License :: OSI Approved :: MIT License
Classifier: Programming Language :: Python
Classifier: Programming Language :: Python :: 2.4
Classifier: Programming Language :: Python :: 2.5
Classifier: Programming Language :: Python :: 2.6
Classifier: Topic :: Internet :: WWW/HTTP
Classifier: Topic :: Internet :: WWW/HTTP :: Dynamic Content
Classifier: Topic :: Software Development :: Code Generators
